agent/Q.py
agent/__init__.py
agent/epsilon_greedy_policy.py
agent/my_agent.py
agent/policy_interface.py
agent/typing.py
controllers/__init__.py
controllers/action_set.py
controllers/action_space.py
controllers/typing.py
locators/__init__.py
locators/fixed_locator.py
locators/locator_interface.py
locators/random_locator.py
qlib_learn-1.0.3.dist-info/licenses/LICENSE
reward_strategy/__init__.py
reward_strategy/reward_distance.py
reward_strategy/reward_interface.py
reward_strategy/typing.py
search/__init__.py
search/object_search.py
spaces/__init__.py
spaces/entity_channel_map.py
spaces/observation_grid.py
spaces/observation_space.py
trainment/__init__.py
trainment/training.py
utils/__init__.py
utils/geo_coordinate.py
qlib_learn-1.0.3.dist-info/METADATA
qlib_learn-1.0.3.dist-info/WHEEL
qlib_learn-1.0.3.dist-info/top_level.txt
qlib_learn-1.0.3.dist-info/RECORD
